[
  {
    "name": "Tech for Good Hackathon",
    "date": "2025-03-20",
    "location": "New York",
    "skills": ["JavaScript", "Python", "AI"],
    "description": "A hackathon focused on technology solutions for social impact."
  },
  {
    "name": "Community Cleanup Drive",
    "date": "2025-04-05",
    "location": "Los Angeles",
    "skills": ["Teamwork", "Public Speaking"],
    "description": "Join us to clean up parks and spread awareness about waste management."
  },
  {
    "name": "Mental Health Awareness Webinar",
    "date": "2025-03-15",
    "location": "San Francisco",
    "skills": ["Counseling", "Communication"],
    "description": "An online event discussing mental health challenges and support systems."
  },
  {
    "name": "Code for Climate",
    "date": "2025-05-10",
    "location": "Chicago",
    "skills": ["Python", "Data Science"],
    "description": "Develop AI-based solutions to tackle climate change issues."
  },
  {
    "name": "Cleanliness Drive - Mumbai Beach",
    "date": "2025-03-15",
    "location": "Juhu Beach, Mumbai",
    "skills": ["Teamwork", "Environmental Awareness"],
    "description": "Join us for a beach cleanup to make Mumbai's coastline cleaner!"
  },
  {
    "name": "Tech for Good - AI for NGOs",
    "date": "2025-04-10",
    "location": "Bangalore",
    "skills": ["Machine Learning", "Data Science", "AI"],
    "description": "A workshop on how AI can help NGOs streamline their work."
  },
  {
    "name": "Tree Plantation Drive",
    "date": "2025-03-25",
    "location": "Delhi",
    "skills": ["Gardening", "Sustainability"],
    "description": "Plant trees in urban areas to make Delhi greener!"
  },
  {
    "name": "Blood Donation Camp",
    "date": "2025-02-28",
    "location": "Pune",
    "skills": ["Medical Knowledge", "Public Relations"],
    "description": "Donate blood and save lives. Volunteers needed to manage registrations."
  },
  {
    "name": "Teaching Underprivileged Kids",
    "date": "2025-05-01",
    "location": "Kolkata",
    "skills": ["Teaching", "Communication"],
    "description": "Help educate children from low-income backgrounds."
  },
  {
    "name": "Animal Welfare Drive",
    "date": "2025-03-20",
    "location": "Chennai",
    "skills": ["Animal Care", "Empathy"],
    "description": "Assist in rescuing and caring for stray animals."
  },
  {
    "name": "Women's Safety Awareness Campaign",
    "date": "2025-04-05",
    "location": "Hyderabad",
    "skills": ["Public Speaking", "Self-defense"],
    "description": "An initiative to educate and empower women regarding safety measures."
  },
  {
    "name": "Recycling & Waste Management Workshop",
    "date": "2025-04-18",
    "location": "Ahmedabad",
    "skills": ["Sustainability", "Problem-Solving"],
    "description": "Learn how to recycle and manage waste effectively."
  },
  {
    "name": "Elderly Care Volunteering",
    "date": "2025-03-22",
    "location": "Jaipur",
    "skills": ["Compassion", "Patience"],
    "description": "Spend time with senior citizens and help them with daily activities."
  },
  {
    "name": "Village Digital Literacy Program",
    "date": "2025-06-10",
    "location": "Varanasi",
    "skills": ["Teaching", "Computer Basics"],
    "description": "Teach basic computer skills to villagers to improve digital literacy."
  },
  {
    "name": "Flood Relief Support",
    "date": "2025-07-05",
    "location": "Assam",
    "skills": ["Disaster Management", "First Aid"],
    "description": "Help distribute relief material and provide support to flood-affected areas."
  },
  {
    "name": "Women Entrepreneurship Bootcamp",
    "date": "2025-08-12",
    "location": "Bhopal",
    "skills": ["Business Planning", "Finance"],
    "description": "Support women entrepreneurs by mentoring them in starting businesses."
  },
  {
    "name": "AI for Social Good Hackathon",
    "date": "2025-09-02",
    "location": "Hyderabad",
    "skills": ["Python", "AI/ML"],
    "description": "Build AI-powered solutions for real-world social challenges."
  },
  {
    "name": "Rural Healthcare Awareness Camp",
    "date": "2025-06-20",
    "location": "Nagpur",
    "skills": ["Medical Knowledge", "Communication"],
    "description": "Spread awareness about hygiene, nutrition, and common diseases."
  },
  {
    "name": "Public Transport Accessibility Survey",
    "date": "2025-07-18",
    "location": "Lucknow",
    "skills": ["Data Collection", "Problem-Solving"],
    "description": "Assist in surveying local transportation to improve accessibility."
  },
  {
    "name": "Underprivileged Kids' Art Workshop",
    "date": "2025-08-07",
    "location": "Chandigarh",
    "skills": ["Painting", "Creativity"],
    "description": "Conduct an art session to help children express creativity."
  },
  {
    "name": "Coding for Beginners - Free Workshop",
    "date": "2025-06-30",
    "location": "Bangalore",
    "skills": ["JavaScript", "Web Development"],
    "description": "A free coding bootcamp for students with no prior experience."
  },
  {
    "name": "Mental Health Support Group",
    "date": "2025-09-15",
    "location": "Jaipur",
    "skills": ["Counseling", "Active Listening"],
    "description": "Facilitate discussions on mental well-being and provide peer support."
  },
  {
    "name": "Plastic-Free City Awareness Drive",
    "date": "2025-07-22",
    "location": "Indore",
    "skills": ["Public Speaking", "Community Outreach"],
    "description": "Spread awareness about reducing plastic usage in urban areas."
  },
  {
    "name": "Elderly Home Assistance Program",
    "date": "2025-10-05",
    "location": "Mysore",
    "skills": ["Empathy", "Caregiving"],
    "description": "Help elderly citizens by engaging in recreational activities."
  },
  {
    "name": "Renewable Energy Workshop",
    "date": "2025-09-25",
    "location": "Kochi",
    "skills": ["Sustainability", "Solar Energy"],
    "description": "Educate students about renewable energy and its applications."
  },
  {
    "name": "Sports for Youth Development",
    "date": "2025-08-10",
    "location": "Kolkata",
    "skills": ["Coaching", "Leadership"],
    "description": "Encourage sports participation among underprivileged kids."
  },
  {
    "name": "Sign Language Learning Workshop",
    "date": "2025-06-29",
    "location": "Delhi",
    "skills": ["Sign Language", "Inclusive Communication"],
    "description": "Teach basic sign language to promote inclusivity."
  },
  {
    "name": "Safe Cycling & Road Safety Initiative",
    "date": "2025-08-20",
    "location": "Ahmedabad",
    "skills": ["Traffic Rules", "Public Speaking"],
    "description": "Spread awareness on safe cycling and responsible road behavior."
  },
  {
    "name": "STEM Workshop for Girls",
    "date": "2025-07-12",
    "location": "Bangalore",
    "skills": ["Science", "Coding"],
    "description": "Encourage young girls to explore STEM fields."
  },
  {
    "name": "Food Waste Reduction Campaign",
    "date": "2025-09-05",
    "location": "Pune",
    "skills": ["Sustainability", "Community Engagement"],
    "description": "Educate restaurants and households on reducing food wastage."
  },
  {
    "name": "Cancer Awareness Fundraiser",
    "date": "2025-10-15",
    "location": "Hyderabad",
    "skills": ["Event Management", "Marketing"],
    "description": "Organize a fundraiser to support cancer treatment programs."
  },
  {
    "name": "Tech Training for Senior Citizens",
    "date": "2025-08-28",
    "location": "Mumbai",
    "skills": ["Basic Computing", "Patience"],
    "description": "Help seniors learn how to use smartphones and the internet."
  },
  {
    "name": "DIY Home Gardening Workshop",
    "date": "2025-07-30",
    "location": "Chennai",
    "skills": ["Gardening", "Composting"],
    "description": "Learn about organic gardening and sustainable farming techniques."
  },
  {
    "name": "Book Donation & Literacy Drive",
    "date": "2025-09-08",
    "location": "Patna",
    "skills": ["Organizing", "Teaching"],
    "description": "Donate books and tutor underprivileged students."
  },
  {
    "name": "Cyber Security Awareness Drive",
    "date": "2025-06-22",
    "location": "Noida",
    "skills": ["Cybersecurity", "Public Awareness"],
    "description": "Teach people about online safety and fraud prevention."
  },
  {
    "name": "AI in Healthcare Panel Discussion",
    "date": "2025-07-14",
    "location": "Bangalore",
    "skills": ["Healthcare", "Artificial Intelligence"],
    "description": "Experts discuss AI advancements in the healthcare industry."
  },
  {
    "name": "Financial Literacy for Youth",
    "date": "2025-08-15",
    "location": "Nagpur",
    "skills": ["Finance", "Budgeting"],
    "description": "Teach college students about savings and investments."
  },
  {
    "name": "Zero-Waste Lifestyle Workshop",
    "date": "2025-09-22",
    "location": "Surat",
    "skills": ["Sustainability", "Recycling"],
    "description": "Learn how to live a zero-waste lifestyle and reduce landfill waste."
  },
  {
    "name": "Disaster Preparedness & Relief Training",
    "date": "2025-10-10",
    "location": "Bhubaneswar",
    "skills": ["Emergency Response", "Community Leadership"],
    "description": "Train volunteers for disaster relief and emergency response."
  },
  {
    "name": "Community Murals & Street Art Festival",
    "date": "2025-09-01",
    "location": "Jaipur",
    "skills": ["Painting", "Creativity"],
    "description": "Beautify public spaces through street art and murals."
  },
  {
    "name": "Ethical Hacking Workshop",
    "date": "2025-08-25",
    "location": "Chennai",
    "skills": ["Cybersecurity", "Ethical Hacking"],
    "description": "Learn about ethical hacking and cyber threat detection."
  },
  {
    "name": "AI for Accessibility - Tech Event",
    "date": "2025-07-17",
    "location": "Delhi",
    "skills": ["Machine Learning", "UX Design"],
    "description": "Develop AI-based solutions for improving accessibility."
  }

  
]

   
   
   
   
   
  